{
 "MC2 ": [ 
  {
   "OBJT": [ 
    {
     "CLID": {
      "class_id": "base.class"
     }
    }, 
    {
     "BASE": [ 
      {
       "ROOT": [ 
        {
         "NAME": {
          "name": "VP_SULG1",
          "zero_terminated": false
         }
        } ]
      }, 
      {
       "STRC": {
        "_un1": 0,
        "ambient_light": 255,
        "att_flags": 72,
        "ax": 0,
        "ay": 0,
        "az": 0,
        "pos": [ 0.0, 0.0, 0.0 ],
        "rx": 0,
        "ry": 0,
        "rz": 0,
        "scale": [ 1.0, 1.0, 1.0 ],
        "strc_type": "STRC_BASE",
        "vec": [ 0.0, 0.0, 0.0 ],
        "version": 1,
        "vis_limit": 4096
       }
      }, 
      {
       "OBJT": [ 
        {
         "CLID": {
          "class_id": "sklt.class"
         }
        }, 
        {
         "SKLC": [ 
          {
           "NAME": {
            "name": "Skeleton/VP_SULG1.sklt",
            "zero_terminated": true
           }
          } ]
        } ]
      }, 
      {
       "ADES": [ 
        {
         "OBJT": [ 
          {
           "CLID": {
            "class_id": "amesh.class"
           }
          }, 
          {
           "AMSH": [ 
            {
             "AREA": [ 
              {
               "ADE ": [ 
                {
                 "ROOT": []
                }, 
                {
                 "STRC": {
                  "_nu2": 0,
                  "_nul": 0,
                  "flags": 2,
                  "point": 0,
                  "poly": 0,
                  "strc_type": "STRC_ADE ",
                  "version": 1
                 }
                } ]
              }, 
              {
               "STRC": {
                "_un1": 0,
                "clrVal": 1,
                "flags": 1,
                "polFlags": 62,
                "shdVal": 0,
                "strc_type": "STRC_AREA",
                "trcVal": 0,
                "version": 256
               }
              }, 
              {
               "OBJT": [ 
                {
                 "CLID": {
                  "class_id": "ilbm.class"
                 }
                }, 
                {
                 "CIBO": [ 
                  {
                   "NAM2": {
                    "name": "FBAGGER.ILBM",
                    "zero_terminated": true
                   }
                  } ]
                } ]
              } ]
            }, 
            {
             "ATTS": {
              "atts_entries": [ 
               {
                "color_val": 0,
                "pad": 0,
                "poly_id": 0,
                "shade_val": 175,
                "tracy_val": 128
               }, 
               {
                "color_val": 0,
                "pad": 0,
                "poly_id": 1,
                "shade_val": 110,
                "tracy_val": 128
               }, 
               {
                "color_val": 0,
                "pad": 0,
                "poly_id": 2,
                "shade_val": 150,
                "tracy_val": 128
               }, 
               {
                "color_val": 0,
                "pad": 0,
                "poly_id": 3,
                "shade_val": 200,
                "tracy_val": 128
               }, 
               {
                "color_val": 0,
                "pad": 0,
                "poly_id": 4,
                "shade_val": 179,
                "tracy_val": 128
               }, 
               {
                "color_val": 0,
                "pad": 0,
                "poly_id": 5,
                "shade_val": 165,
                "tracy_val": 128
               }, 
               {
                "color_val": 0,
                "pad": 0,
                "poly_id": 6,
                "shade_val": 179,
                "tracy_val": 128
               }, 
               {
                "color_val": 0,
                "pad": 0,
                "poly_id": 7,
                "shade_val": 180,
                "tracy_val": 128
               }, 
               {
                "color_val": 0,
                "pad": 0,
                "poly_id": 8,
                "shade_val": 160,
                "tracy_val": 128
               }, 
               {
                "color_val": 0,
                "pad": 0,
                "poly_id": 9,
                "shade_val": 100,
                "tracy_val": 128
               }, 
               {
                "color_val": 0,
                "pad": 0,
                "poly_id": 10,
                "shade_val": 120,
                "tracy_val": 128
               }, 
               {
                "color_val": 0,
                "pad": 0,
                "poly_id": 11,
                "shade_val": 75,
                "tracy_val": 128
               }, 
               {
                "color_val": 0,
                "pad": 0,
                "poly_id": 12,
                "shade_val": 100,
                "tracy_val": 128
               }, 
               {
                "color_val": 0,
                "pad": 0,
                "poly_id": 13,
                "shade_val": 140,
                "tracy_val": 128
               }, 
               {
                "color_val": 0,
                "pad": 0,
                "poly_id": 14,
                "shade_val": 160,
                "tracy_val": 128
               }, 
               {
                "color_val": 0,
                "pad": 0,
                "poly_id": 15,
                "shade_val": 110,
                "tracy_val": 128
               }, 
               {
                "color_val": 0,
                "pad": 0,
                "poly_id": 16,
                "shade_val": 140,
                "tracy_val": 128
               }, 
               {
                "color_val": 0,
                "pad": 0,
                "poly_id": 17,
                "shade_val": 100,
                "tracy_val": 128
               }, 
               {
                "color_val": 0,
                "pad": 0,
                "poly_id": 18,
                "shade_val": 70,
                "tracy_val": 128
               }, 
               {
                "color_val": 0,
                "pad": 0,
                "poly_id": 19,
                "shade_val": 100,
                "tracy_val": 128
               }, 
               {
                "color_val": 0,
                "pad": 0,
                "poly_id": 20,
                "shade_val": 120,
                "tracy_val": 128
               }, 
               {
                "color_val": 0,
                "pad": 0,
                "poly_id": 21,
                "shade_val": 150,
                "tracy_val": 128
               }, 
               {
                "color_val": 0,
                "pad": 0,
                "poly_id": 22,
                "shade_val": 140,
                "tracy_val": 128
               }, 
               {
                "color_val": 0,
                "pad": 0,
                "poly_id": 23,
                "shade_val": 160,
                "tracy_val": 128
               }, 
               {
                "color_val": 0,
                "pad": 0,
                "poly_id": 24,
                "shade_val": 165,
                "tracy_val": 128
               }, 
               {
                "color_val": 0,
                "pad": 0,
                "poly_id": 25,
                "shade_val": 179,
                "tracy_val": 128
               }, 
               {
                "color_val": 0,
                "pad": 0,
                "poly_id": 26,
                "shade_val": 100,
                "tracy_val": 128
               }, 
               {
                "color_val": 0,
                "pad": 0,
                "poly_id": 27,
                "shade_val": 190,
                "tracy_val": 128
               }, 
               {
                "color_val": 0,
                "pad": 0,
                "poly_id": 28,
                "shade_val": 140,
                "tracy_val": 128
               }, 
               {
                "color_val": 0,
                "pad": 0,
                "poly_id": 29,
                "shade_val": 160,
                "tracy_val": 128
               }, 
               {
                "color_val": 0,
                "pad": 0,
                "poly_id": 30,
                "shade_val": 150,
                "tracy_val": 128
               }, 
               {
                "color_val": 0,
                "pad": 0,
                "poly_id": 31,
                "shade_val": 130,
                "tracy_val": 128
               }, 
               {
                "color_val": 0,
                "pad": 0,
                "poly_id": 32,
                "shade_val": 140,
                "tracy_val": 128
               }, 
               {
                "color_val": 0,
                "pad": 0,
                "poly_id": 33,
                "shade_val": 120,
                "tracy_val": 128
               } ],
              "is_particle_atts": false
             }
            }, 
            {
             "OLPL": {
              "points": [ 
               [ 
                [ 228, 70 ], 
                [ 229, 50 ], 
                [ 251, 50 ], 
                [ 251, 70 ] ], 
               [ 
                [ 167, 41 ], 
                [ 146, 8 ], 
                [ 191, 12 ] ], 
               [ 
                [ 198, 70 ], 
                [ 199, 50 ], 
                [ 229, 50 ], 
                [ 228, 70 ] ], 
               [ 
                [ 229, 50 ], 
                [ 230, 89 ], 
                [ 251, 89 ], 
                [ 251, 50 ] ], 
               [ 
                [ 230, 30 ], 
                [ 232, 22 ], 
                [ 250, 22 ], 
                [ 251, 30 ] ], 
               [ 
                [ 199, 50 ], 
                [ 202, 30 ], 
                [ 230, 30 ], 
                [ 229, 50 ] ], 
               [ 
                [ 202, 30 ], 
                [ 205, 22 ], 
                [ 232, 22 ], 
                [ 230, 30 ] ], 
               [ 
                [ 232, 79 ], 
                [ 235, 50 ], 
                [ 247, 50 ], 
                [ 250, 79 ] ], 
               [ 
                [ 205, 79 ], 
                [ 211, 50 ], 
                [ 235, 50 ], 
                [ 232, 79 ] ], 
               [ 
                [ 167, 41 ], 
                [ 128, 41 ], 
                [ 146, 8 ] ], 
               [ 
                [ 174, 70 ], 
                [ 173, 50 ], 
                [ 199, 50 ], 
                [ 198, 70 ] ], 
               [ 
                [ 167, 41 ], 
                [ 146, 75 ], 
                [ 128, 41 ] ], 
               [ 
                [ 148, 70 ], 
                [ 147, 50 ], 
                [ 173, 50 ], 
                [ 174, 70 ] ], 
               [ 
                [ 173, 50 ], 
                [ 174, 30 ], 
                [ 202, 30 ], 
                [ 199, 50 ] ], 
               [ 
                [ 174, 30 ], 
                [ 174, 22 ], 
                [ 205, 22 ], 
                [ 202, 30 ] ], 
               [ 
                [ 147, 50 ], 
                [ 145, 30 ], 
                [ 174, 30 ], 
                [ 173, 50 ] ], 
               [ 
                [ 145, 30 ], 
                [ 144, 22 ], 
                [ 174, 22 ], 
                [ 174, 30 ] ], 
               [ 
                [ 174, 79 ], 
                [ 174, 50 ], 
                [ 211, 50 ], 
                [ 205, 79 ] ], 
               [ 
                [ 144, 79 ], 
                [ 142, 50 ], 
                [ 174, 50 ], 
                [ 174, 79 ] ], 
               [ 
                [ 167, 41 ], 
                [ 190, 71 ], 
                [ 146, 75 ] ], 
               [ 
                [ 119, 70 ], 
                [ 118, 50 ], 
                [ 147, 50 ], 
                [ 148, 70 ] ], 
               [ 
                [ 96, 70 ], 
                [ 96, 50 ], 
                [ 118, 50 ], 
                [ 119, 70 ] ], 
               [ 
                [ 118, 50 ], 
                [ 117, 30 ], 
                [ 145, 30 ], 
                [ 147, 50 ] ], 
               [ 
                [ 117, 30 ], 
                [ 115, 22 ], 
                [ 144, 22 ], 
                [ 145, 30 ] ], 
               [ 
                [ 96, 50 ], 
                [ 96, 30 ], 
                [ 117, 30 ], 
                [ 118, 50 ] ], 
               [ 
                [ 96, 30 ], 
                [ 96, 22 ], 
                [ 115, 22 ], 
                [ 117, 30 ] ], 
               [ 
                [ 115, 79 ], 
                [ 114, 50 ], 
                [ 142, 50 ], 
                [ 144, 79 ] ], 
               [ 
                [ 96, 79 ], 
                [ 96, 50 ], 
                [ 114, 50 ], 
                [ 115, 79 ] ], 
               [ 
                [ 167, 41 ], 
                [ 191, 12 ], 
                [ 192, 32 ] ], 
               [ 
                [ 191, 12 ], 
                [ 217, 42 ], 
                [ 192, 32 ] ], 
               [ 
                [ 217, 42 ], 
                [ 167, 41 ], 
                [ 192, 32 ] ], 
               [ 
                [ 167, 41 ], 
                [ 217, 42 ], 
                [ 192, 51 ] ], 
               [ 
                [ 217, 42 ], 
                [ 190, 71 ], 
                [ 192, 51 ] ], 
               [ 
                [ 190, 71 ], 
                [ 167, 41 ], 
                [ 192, 51 ] ] ]
             }
            } ]
          } ]
        }, 
        {
         "OBJT": [ 
          {
           "CLID": {
            "class_id": "amesh.class"
           }
          }, 
          {
           "AMSH": [ 
            {
             "AREA": [ 
              {
               "ADE ": [ 
                {
                 "ROOT": []
                }, 
                {
                 "STRC": {
                  "_nu2": 0,
                  "_nul": 0,
                  "flags": 0,
                  "point": 0,
                  "poly": 0,
                  "strc_type": "STRC_ADE ",
                  "version": 1
                 }
                } ]
              }, 
              {
               "STRC": {
                "_un1": 0,
                "clrVal": 1,
                "flags": 0,
                "polFlags": 138,
                "shdVal": 0,
                "strc_type": "STRC_AREA",
                "trcVal": 0,
                "version": 256
               }
              }, 
              {
               "OBJT": [ 
                {
                 "CLID": {
                  "class_id": "ilbm.class"
                 }
                }, 
                {
                 "CIBO": [ 
                  {
                   "NAM2": {
                    "name": "FX1.ILBM",
                    "zero_terminated": true
                   }
                  } ]
                } ]
              } ]
            }, 
            {
             "ATTS": {
              "atts_entries": [ 
               {
                "color_val": 0,
                "pad": 0,
                "poly_id": 34,
                "shade_val": 0,
                "tracy_val": 128
               }, 
               {
                "color_val": 0,
                "pad": 0,
                "poly_id": 35,
                "shade_val": 0,
                "tracy_val": 128
               }, 
               {
                "color_val": 0,
                "pad": 0,
                "poly_id": 36,
                "shade_val": 0,
                "tracy_val": 128
               }, 
               {
                "color_val": 0,
                "pad": 0,
                "poly_id": 37,
                "shade_val": 0,
                "tracy_val": 128
               }, 
               {
                "color_val": 0,
                "pad": 0,
                "poly_id": 38,
                "shade_val": 0,
                "tracy_val": 128
               }, 
               {
                "color_val": 0,
                "pad": 0,
                "poly_id": 39,
                "shade_val": 0,
                "tracy_val": 128
               }, 
               {
                "color_val": 0,
                "pad": 0,
                "poly_id": 40,
                "shade_val": 0,
                "tracy_val": 128
               }, 
               {
                "color_val": 0,
                "pad": 0,
                "poly_id": 41,
                "shade_val": 0,
                "tracy_val": 128
               }, 
               {
                "color_val": 0,
                "pad": 0,
                "poly_id": 42,
                "shade_val": 0,
                "tracy_val": 128
               }, 
               {
                "color_val": 0,
                "pad": 0,
                "poly_id": 43,
                "shade_val": 0,
                "tracy_val": 128
               }, 
               {
                "color_val": 0,
                "pad": 0,
                "poly_id": 44,
                "shade_val": 0,
                "tracy_val": 128
               }, 
               {
                "color_val": 0,
                "pad": 0,
                "poly_id": 45,
                "shade_val": 0,
                "tracy_val": 128
               }, 
               {
                "color_val": 0,
                "pad": 0,
                "poly_id": 46,
                "shade_val": 0,
                "tracy_val": 128
               }, 
               {
                "color_val": 0,
                "pad": 0,
                "poly_id": 47,
                "shade_val": 0,
                "tracy_val": 128
               }, 
               {
                "color_val": 0,
                "pad": 0,
                "poly_id": 48,
                "shade_val": 0,
                "tracy_val": 128
               }, 
               {
                "color_val": 0,
                "pad": 0,
                "poly_id": 49,
                "shade_val": 0,
                "tracy_val": 128
               } ],
              "is_particle_atts": false
             }
            }, 
            {
             "OLPL": {
              "points": [ 
               [ 
                [ 1, 68 ], 
                [ 1, 33 ], 
                [ 129, 45 ] ], 
               [ 
                [ 1, 68 ], 
                [ 1, 33 ], 
                [ 129, 45 ] ], 
               [ 
                [ 1, 68 ], 
                [ 1, 33 ], 
                [ 129, 45 ] ], 
               [ 
                [ 1, 68 ], 
                [ 1, 33 ], 
                [ 129, 45 ] ], 
               [ 
                [ 1, 68 ], 
                [ 1, 33 ], 
                [ 129, 45 ] ], 
               [ 
                [ 1, 68 ], 
                [ 1, 33 ], 
                [ 129, 45 ] ], 
               [ 
                [ 1, 68 ], 
                [ 1, 33 ], 
                [ 129, 45 ] ], 
               [ 
                [ 1, 68 ], 
                [ 1, 33 ], 
                [ 129, 45 ] ], 
               [ 
                [ 1, 68 ], 
                [ 1, 33 ], 
                [ 129, 45 ] ], 
               [ 
                [ 1, 68 ], 
                [ 1, 33 ], 
                [ 129, 45 ] ], 
               [ 
                [ 1, 68 ], 
                [ 1, 33 ], 
                [ 129, 45 ] ], 
               [ 
                [ 1, 68 ], 
                [ 1, 33 ], 
                [ 129, 45 ] ], 
               [ 
                [ 1, 68 ], 
                [ 1, 33 ], 
                [ 129, 45 ] ], 
               [ 
                [ 1, 68 ], 
                [ 1, 33 ], 
                [ 129, 45 ] ], 
               [ 
                [ 1, 68 ], 
                [ 1, 33 ], 
                [ 129, 45 ] ], 
               [ 
                [ 1, 68 ], 
                [ 1, 33 ], 
                [ 129, 45 ] ] ]
             }
            } ]
          } ]
        } ]
      } ]
    } ]
  } ]
}