{
 "MC2 ": [ 
  {
   "OBJT": [ 
    {
     "CLID": {
      "class_id": "base.class"
     }
    }, 
    {
     "BASE": [ 
      {
       "ROOT": [ 
        {
         "NAME": {
          "name": "WGySPHNX",
          "zero_terminated": false
         }
        } ]
      }, 
      {
       "STRC": {
        "_un1": 0,
        "ambient_light": 255,
        "att_flags": 72,
        "ax": 0,
        "ay": 0,
        "az": 0,
        "pos": [ 0.0, 0.0, 0.0 ],
        "rx": 0,
        "ry": 0,
        "rz": 0,
        "scale": [ 1.0, 1.0, 1.0 ],
        "strc_type": "STRC_BASE",
        "vec": [ 0.0, 0.0, 0.0 ],
        "version": 1,
        "vis_limit": 4096
       }
      }, 
      {
       "OBJT": [ 
        {
         "CLID": {
          "class_id": "sklt.class"
         }
        }, 
        {
         "SKLC": [ 
          {
           "NAME": {
            "name": "Skeleton/WGYSPHNX.sklt",
            "zero_terminated": true
           }
          } ]
        } ]
      }, 
      {
       "ADES": [ 
        {
         "OBJT": [ 
          {
           "CLID": {
            "class_id": "amesh.class"
           }
          }, 
          {
           "AMSH": [ 
            {
             "AREA": [ 
              {
               "ADE ": [ 
                {
                 "ROOT": []
                }, 
                {
                 "STRC": {
                  "_nu2": 0,
                  "_nul": 0,
                  "flags": 2,
                  "point": 0,
                  "poly": 0,
                  "strc_type": "STRC_ADE ",
                  "version": 1
                 }
                } ]
              }, 
              {
               "STRC": {
                "_un1": 0,
                "clrVal": 1,
                "flags": 1,
                "polFlags": 62,
                "shdVal": 0,
                "strc_type": "STRC_AREA",
                "trcVal": 0,
                "version": 256
               }
              }, 
              {
               "OBJT": [ 
                {
                 "CLID": {
                  "class_id": "ilbm.class"
                 }
                }, 
                {
                 "CIBO": [ 
                  {
                   "NAM2": {
                    "name": "HYPE.ILBM",
                    "zero_terminated": true
                   }
                  } ]
                } ]
              } ]
            }, 
            {
             "ATTS": {
              "atts_entries": [ 
               {
                "color_val": 0,
                "pad": 0,
                "poly_id": 0,
                "shade_val": 95,
                "tracy_val": 128
               }, 
               {
                "color_val": 0,
                "pad": 0,
                "poly_id": 1,
                "shade_val": 0,
                "tracy_val": 128
               }, 
               {
                "color_val": 0,
                "pad": 0,
                "poly_id": 2,
                "shade_val": 99,
                "tracy_val": 128
               }, 
               {
                "color_val": 0,
                "pad": 0,
                "poly_id": 3,
                "shade_val": 41,
                "tracy_val": 128
               }, 
               {
                "color_val": 0,
                "pad": 0,
                "poly_id": 4,
                "shade_val": 48,
                "tracy_val": 128
               }, 
               {
                "color_val": 0,
                "pad": 0,
                "poly_id": 5,
                "shade_val": 45,
                "tracy_val": 128
               }, 
               {
                "color_val": 0,
                "pad": 0,
                "poly_id": 6,
                "shade_val": 42,
                "tracy_val": 128
               }, 
               {
                "color_val": 0,
                "pad": 0,
                "poly_id": 7,
                "shade_val": 97,
                "tracy_val": 128
               }, 
               {
                "color_val": 0,
                "pad": 0,
                "poly_id": 8,
                "shade_val": 94,
                "tracy_val": 128
               }, 
               {
                "color_val": 0,
                "pad": 0,
                "poly_id": 9,
                "shade_val": 97,
                "tracy_val": 128
               }, 
               {
                "color_val": 0,
                "pad": 0,
                "poly_id": 10,
                "shade_val": 94,
                "tracy_val": 128
               }, 
               {
                "color_val": 0,
                "pad": 0,
                "poly_id": 11,
                "shade_val": 0,
                "tracy_val": 128
               }, 
               {
                "color_val": 0,
                "pad": 0,
                "poly_id": 12,
                "shade_val": 0,
                "tracy_val": 128
               }, 
               {
                "color_val": 0,
                "pad": 0,
                "poly_id": 13,
                "shade_val": 99,
                "tracy_val": 128
               }, 
               {
                "color_val": 0,
                "pad": 0,
                "poly_id": 14,
                "shade_val": 96,
                "tracy_val": 128
               }, 
               {
                "color_val": 0,
                "pad": 0,
                "poly_id": 15,
                "shade_val": 0,
                "tracy_val": 128
               }, 
               {
                "color_val": 0,
                "pad": 0,
                "poly_id": 16,
                "shade_val": 9,
                "tracy_val": 128
               }, 
               {
                "color_val": 0,
                "pad": 0,
                "poly_id": 17,
                "shade_val": 99,
                "tracy_val": 128
               }, 
               {
                "color_val": 0,
                "pad": 0,
                "poly_id": 18,
                "shade_val": 96,
                "tracy_val": 128
               }, 
               {
                "color_val": 0,
                "pad": 0,
                "poly_id": 19,
                "shade_val": 99,
                "tracy_val": 128
               }, 
               {
                "color_val": 0,
                "pad": 0,
                "poly_id": 20,
                "shade_val": 60,
                "tracy_val": 128
               }, 
               {
                "color_val": 0,
                "pad": 0,
                "poly_id": 21,
                "shade_val": 0,
                "tracy_val": 128
               }, 
               {
                "color_val": 0,
                "pad": 0,
                "poly_id": 22,
                "shade_val": 0,
                "tracy_val": 128
               }, 
               {
                "color_val": 0,
                "pad": 0,
                "poly_id": 23,
                "shade_val": 0,
                "tracy_val": 128
               }, 
               {
                "color_val": 0,
                "pad": 0,
                "poly_id": 24,
                "shade_val": 0,
                "tracy_val": 128
               }, 
               {
                "color_val": 0,
                "pad": 0,
                "poly_id": 55,
                "shade_val": 96,
                "tracy_val": 128
               }, 
               {
                "color_val": 0,
                "pad": 0,
                "poly_id": 56,
                "shade_val": 96,
                "tracy_val": 128
               }, 
               {
                "color_val": 0,
                "pad": 0,
                "poly_id": 57,
                "shade_val": 99,
                "tracy_val": 128
               }, 
               {
                "color_val": 0,
                "pad": 0,
                "poly_id": 58,
                "shade_val": 99,
                "tracy_val": 128
               } ],
              "is_particle_atts": false
             }
            }, 
            {
             "OLPL": {
              "points": [ 
               [ 
                [ 253, 6 ], 
                [ 151, 55 ], 
                [ 168, 118 ] ], 
               [ 
                [ 254, 6 ], 
                [ 151, 55 ], 
                [ 174, 117 ] ], 
               [ 
                [ 228, 48 ], 
                [ 228, 117 ], 
                [ 169, 117 ], 
                [ 169, 48 ] ], 
               [ 
                [ 253, 5 ], 
                [ 150, 54 ], 
                [ 150, 117 ] ], 
               [ 
                [ 150, 117 ], 
                [ 254, 117 ], 
                [ 253, 5 ] ], 
               [ 
                [ 254, 6 ], 
                [ 151, 55 ], 
                [ 151, 118 ] ], 
               [ 
                [ 151, 118 ], 
                [ 255, 118 ], 
                [ 254, 6 ] ], 
               [ 
                [ 253, 5 ], 
                [ 149, 54 ], 
                [ 253, 117 ] ], 
               [ 
                [ 149, 54 ], 
                [ 149, 117 ], 
                [ 253, 117 ] ], 
               [ 
                [ 1, 2 ], 
                [ 100, 2 ], 
                [ 1, 113 ] ], 
               [ 
                [ 100, 2 ], 
                [ 99, 68 ], 
                [ 1, 113 ] ], 
               [ 
                [ 159, 44 ], 
                [ 84, 44 ], 
                [ 159, 1 ] ], 
               [ 
                [ 84, 44 ], 
                [ 84, 1 ], 
                [ 159, 1 ] ], 
               [ 
                [ 231, 117 ], 
                [ 252, 6 ], 
                [ 149, 116 ] ], 
               [ 
                [ 252, 6 ], 
                [ 150, 55 ], 
                [ 149, 116 ] ], 
               [ 
                [ 150, 115 ], 
                [ 151, 54 ], 
                [ 253, 5 ] ], 
               [ 
                [ 253, 5 ], 
                [ 232, 116 ], 
                [ 150, 115 ] ], 
               [ 
                [ 230, 118 ], 
                [ 251, 7 ], 
                [ 149, 117 ] ], 
               [ 
                [ 251, 7 ], 
                [ 149, 56 ], 
                [ 149, 117 ] ], 
               [ 
                [ 253, 5 ], 
                [ 232, 116 ], 
                [ 150, 115 ] ], 
               [ 
                [ 150, 115 ], 
                [ 151, 54 ], 
                [ 253, 5 ] ], 
               [ 
                [ 169, 48 ], 
                [ 168, 114 ], 
                [ 90, 79 ] ], 
               [ 
                [ 168, 114 ], 
                [ 89, 116 ], 
                [ 90, 79 ] ], 
               [ 
                [ 169, 48 ], 
                [ 168, 114 ], 
                [ 90, 79 ] ], 
               [ 
                [ 168, 114 ], 
                [ 89, 116 ], 
                [ 90, 79 ] ], 
               [ 
                [ 152, 117 ], 
                [ 152, 54 ], 
                [ 244, 117 ] ], 
               [ 
                [ 152, 54 ], 
                [ 244, 54 ], 
                [ 244, 117 ] ], 
               [ 
                [ 228, 48 ], 
                [ 228, 117 ], 
                [ 169, 48 ] ], 
               [ 
                [ 228, 117 ], 
                [ 169, 117 ], 
                [ 169, 48 ] ] ]
             }
            } ]
          } ]
        }, 
        {
         "OBJT": [ 
          {
           "CLID": {
            "class_id": "amesh.class"
           }
          }, 
          {
           "AMSH": [ 
            {
             "AREA": [ 
              {
               "ADE ": [ 
                {
                 "ROOT": []
                }, 
                {
                 "STRC": {
                  "_nu2": 0,
                  "_nul": 0,
                  "flags": 2,
                  "point": 0,
                  "poly": 0,
                  "strc_type": "STRC_ADE ",
                  "version": 1
                 }
                } ]
              }, 
              {
               "STRC": {
                "_un1": 0,
                "clrVal": 1,
                "flags": 1,
                "polFlags": 62,
                "shdVal": 0,
                "strc_type": "STRC_AREA",
                "trcVal": 0,
                "version": 256
               }
              }, 
              {
               "OBJT": [ 
                {
                 "CLID": {
                  "class_id": "ilbm.class"
                 }
                }, 
                {
                 "CIBO": [ 
                  {
                   "NAM2": {
                    "name": "BODEN1.ILBM",
                    "zero_terminated": true
                   }
                  } ]
                } ]
              } ]
            }, 
            {
             "ATTS": {
              "atts_entries": [ 
               {
                "color_val": 0,
                "pad": 0,
                "poly_id": 25,
                "shade_val": 0,
                "tracy_val": 128
               }, 
               {
                "color_val": 0,
                "pad": 0,
                "poly_id": 26,
                "shade_val": 0,
                "tracy_val": 128
               }, 
               {
                "color_val": 0,
                "pad": 0,
                "poly_id": 27,
                "shade_val": 0,
                "tracy_val": 128
               }, 
               {
                "color_val": 0,
                "pad": 0,
                "poly_id": 28,
                "shade_val": 50,
                "tracy_val": 128
               }, 
               {
                "color_val": 0,
                "pad": 0,
                "poly_id": 29,
                "shade_val": 0,
                "tracy_val": 128
               }, 
               {
                "color_val": 0,
                "pad": 0,
                "poly_id": 30,
                "shade_val": 0,
                "tracy_val": 128
               }, 
               {
                "color_val": 0,
                "pad": 0,
                "poly_id": 31,
                "shade_val": 0,
                "tracy_val": 128
               }, 
               {
                "color_val": 0,
                "pad": 0,
                "poly_id": 32,
                "shade_val": 50,
                "tracy_val": 128
               }, 
               {
                "color_val": 0,
                "pad": 0,
                "poly_id": 33,
                "shade_val": 0,
                "tracy_val": 128
               }, 
               {
                "color_val": 0,
                "pad": 0,
                "poly_id": 34,
                "shade_val": 50,
                "tracy_val": 128
               }, 
               {
                "color_val": 0,
                "pad": 0,
                "poly_id": 35,
                "shade_val": 0,
                "tracy_val": 128
               }, 
               {
                "color_val": 0,
                "pad": 0,
                "poly_id": 36,
                "shade_val": 0,
                "tracy_val": 128
               }, 
               {
                "color_val": 0,
                "pad": 0,
                "poly_id": 37,
                "shade_val": 50,
                "tracy_val": 128
               }, 
               {
                "color_val": 0,
                "pad": 0,
                "poly_id": 38,
                "shade_val": 50,
                "tracy_val": 128
               }, 
               {
                "color_val": 0,
                "pad": 0,
                "poly_id": 39,
                "shade_val": 0,
                "tracy_val": 128
               }, 
               {
                "color_val": 0,
                "pad": 0,
                "poly_id": 40,
                "shade_val": 0,
                "tracy_val": 128
               }, 
               {
                "color_val": 0,
                "pad": 0,
                "poly_id": 41,
                "shade_val": 50,
                "tracy_val": 128
               }, 
               {
                "color_val": 0,
                "pad": 0,
                "poly_id": 42,
                "shade_val": 0,
                "tracy_val": 128
               }, 
               {
                "color_val": 0,
                "pad": 0,
                "poly_id": 43,
                "shade_val": 0,
                "tracy_val": 128
               }, 
               {
                "color_val": 0,
                "pad": 0,
                "poly_id": 44,
                "shade_val": 0,
                "tracy_val": 128
               }, 
               {
                "color_val": 0,
                "pad": 0,
                "poly_id": 45,
                "shade_val": 50,
                "tracy_val": 128
               }, 
               {
                "color_val": 0,
                "pad": 0,
                "poly_id": 46,
                "shade_val": 50,
                "tracy_val": 128
               }, 
               {
                "color_val": 0,
                "pad": 0,
                "poly_id": 47,
                "shade_val": 0,
                "tracy_val": 128
               }, 
               {
                "color_val": 0,
                "pad": 0,
                "poly_id": 48,
                "shade_val": 0,
                "tracy_val": 128
               }, 
               {
                "color_val": 0,
                "pad": 0,
                "poly_id": 49,
                "shade_val": 0,
                "tracy_val": 128
               }, 
               {
                "color_val": 0,
                "pad": 0,
                "poly_id": 50,
                "shade_val": 73,
                "tracy_val": 128
               }, 
               {
                "color_val": 0,
                "pad": 0,
                "poly_id": 51,
                "shade_val": 73,
                "tracy_val": 128
               }, 
               {
                "color_val": 0,
                "pad": 0,
                "poly_id": 52,
                "shade_val": 73,
                "tracy_val": 128
               }, 
               {
                "color_val": 0,
                "pad": 0,
                "poly_id": 53,
                "shade_val": 73,
                "tracy_val": 128
               }, 
               {
                "color_val": 0,
                "pad": 0,
                "poly_id": 54,
                "shade_val": 73,
                "tracy_val": 128
               } ],
              "is_particle_atts": false
             }
            }, 
            {
             "OLPL": {
              "points": [ 
               [ 
                [ 129, 1 ], 
                [ 254, 1 ], 
                [ 254, 126 ], 
                [ 129, 126 ] ], 
               [ 
                [ 129, 1 ], 
                [ 254, 1 ], 
                [ 254, 126 ], 
                [ 129, 126 ] ], 
               [ 
                [ 129, 1 ], 
                [ 254, 1 ], 
                [ 254, 126 ], 
                [ 129, 126 ] ], 
               [ 
                [ 162, 1 ], 
                [ 254, 1 ], 
                [ 254, 13 ], 
                [ 201, 12 ] ], 
               [ 
                [ 162, 126 ], 
                [ 201, 114 ], 
                [ 254, 113 ], 
                [ 254, 126 ] ], 
               [ 
                [ 162, 38 ], 
                [ 201, 61 ], 
                [ 162, 85 ] ], 
               [ 
                [ 129, 1 ], 
                [ 162, 1 ], 
                [ 162, 126 ], 
                [ 129, 126 ] ], 
               [ 
                [ 129, 1 ], 
                [ 254, 1 ], 
                [ 254, 13 ], 
                [ 129, 13 ] ], 
               [ 
                [ 129, 113 ], 
                [ 254, 113 ], 
                [ 254, 126 ], 
                [ 129, 126 ] ], 
               [ 
                [ 129, 1 ], 
                [ 191, 1 ], 
                [ 179, 12 ], 
                [ 129, 13 ] ], 
               [ 
                [ 129, 1 ], 
                [ 191, 1 ], 
                [ 191, 63 ], 
                [ 129, 63 ] ], 
               [ 
                [ 191, 1 ], 
                [ 254, 1 ], 
                [ 254, 63 ], 
                [ 191, 63 ] ], 
               [ 
                [ 191, 63 ], 
                [ 254, 63 ], 
                [ 254, 126 ], 
                [ 191, 126 ] ], 
               [ 
                [ 191, 63 ], 
                [ 191, 126 ], 
                [ 160, 126 ] ], 
               [ 
                [ 160, 126 ], 
                [ 129, 126 ], 
                [ 129, 63 ], 
                [ 191, 63 ] ], 
               [ 
                [ 129, 1 ], 
                [ 254, 1 ], 
                [ 254, 63 ], 
                [ 129, 63 ] ], 
               [ 
                [ 129, 63 ], 
                [ 254, 63 ], 
                [ 254, 126 ], 
                [ 129, 126 ] ], 
               [ 
                [ 129, 1 ], 
                [ 191, 1 ], 
                [ 191, 63 ], 
                [ 129, 63 ] ], 
               [ 
                [ 191, 1 ], 
                [ 254, 1 ], 
                [ 254, 63 ], 
                [ 191, 63 ] ], 
               [ 
                [ 191, 63 ], 
                [ 254, 63 ], 
                [ 254, 126 ], 
                [ 191, 126 ] ], 
               [ 
                [ 129, 63 ], 
                [ 191, 63 ], 
                [ 191, 126 ], 
                [ 129, 126 ] ], 
               [ 
                [ 179, 12 ], 
                [ 191, 1 ], 
                [ 191, 96 ], 
                [ 179, 114 ] ], 
               [ 
                [ 129, 113 ], 
                [ 179, 114 ], 
                [ 254, 126 ], 
                [ 129, 126 ] ], 
               [ 
                [ 179, 114 ], 
                [ 191, 96 ], 
                [ 254, 126 ] ], 
               [ 
                [ 191, 96 ], 
                [ 191, 1 ], 
                [ 254, 1 ], 
                [ 254, 126 ] ], 
               [ 
                [ 195, 119 ], 
                [ 141, 110 ], 
                [ 197, 87 ] ], 
               [ 
                [ 195, 119 ], 
                [ 141, 110 ], 
                [ 197, 87 ] ], 
               [ 
                [ 195, 119 ], 
                [ 141, 110 ], 
                [ 197, 87 ] ], 
               [ 
                [ 195, 119 ], 
                [ 141, 110 ], 
                [ 197, 87 ] ], 
               [ 
                [ 195, 119 ], 
                [ 141, 110 ], 
                [ 197, 87 ] ] ]
             }
            } ]
          } ]
        } ]
      } ]
    } ]
  } ]
}